factiva/pipelines/__init__.py
factiva/pipelines/const/__init__.py
factiva/pipelines/metadata/__init__.py
factiva/pipelines/snapshot_files/__init__.py
factiva_pipelines-0.0.1.dist-info/LICENSE
factiva_pipelines-0.0.1.dist-info/METADATA
factiva_pipelines-0.0.1.dist-info/WHEEL
factiva_pipelines-0.0.1.dist-info/top_level.txt
factiva_pipelines-0.0.1.dist-info/RECORD
