Metadata-Version: 2.1
Name: factiva-pipelines
Version: 0.0.1
Summary: Python package with tools to help transforming Snapshots and Streams data.
Home-page: https://github.com/dowjones/factiva-pipelines-python
Author: Miguel Ballesteros
Author-email: miguel.ballesteros@dowjones.com
License: UNKNOWN
Keywords: news,news aggregator,risk,compliance,nlp,alternative data
Platform: UNKNOWN
Classifier: Development Status :: 3 - Alpha
Classifier: Intended Audience :: Science/Research
Classifier: Intended Audience :: Financial and Insurance Industry
Classifier: Operating System :: OS Independent
Classifier: Topic :: Office/Business :: News/Diary
Classifier: Topic :: Office/Business :: Financial :: Investment
Classifier: Topic :: Scientific/Engineering :: Artificial Intelligence
Classifier: License :: OSI Approved :: MIT License
Classifier: Programming Language :: Python :: 3
Classifier: Programming Language :: Python :: 3.5
Classifier: Programming Language :: Python :: 3.6
Classifier: Programming Language :: Python :: 3.7
Classifier: Programming Language :: Python :: 3.8
Requires-Python: >=3.5
Requires-Dist: pandas
Requires-Dist: numpy
Requires-Dist: fastavro
Requires-Dist: textblob
